my_scripts-0.1.0.dist-info/licenses/LICENSE
script_runner/__init__.py
script_runner/cli.py
script_runner/config.py
script_runner/constants.py
script_runner/parser.py
script_runner/commands/__init__.py
script_runner/commands/config_command.py
script_runner/commands/script_command.py
my_scripts-0.1.0.dist-info/METADATA
my_scripts-0.1.0.dist-info/WHEEL
my_scripts-0.1.0.dist-info/entry_points.txt
my_scripts-0.1.0.dist-info/top_level.txt
my_scripts-0.1.0.dist-info/RECORD
