Metadata-Version: 2.4
Name: my-scripts
Version: 0.1.0
Author-email: Sisung Kim <sisung.kim1@gmail.com>
Requires-Python: <4.0,>=3.10
License-File: LICENSE
Requires-Dist: cleo<3.0.0,>=2.1.0
Dynamic: license-file
